django_envtools/__init__.py
django_envtools/_env.py
django_envtools/py.typed
django_envtools/management/__init__.py
django_envtools/management/commands/__init__.py
django_envtools/management/commands/create_env_file.py
django_envtools/management/commands/diff_env_file.py
django_envtools-0.2.0.dist-info/METADATA
django_envtools-0.2.0.dist-info/WHEEL
django_envtools-0.2.0.dist-info/licenses/LICENSE
django_envtools-0.2.0.dist-info/RECORD
