Metadata-Version: 2.4
Name: django-envtools
Version: 0.2.0
Summary: Add your description here
Project-URL: Source, https://github.com/epicserve/django-envtools
Project-URL: Documentation, https://github.com/epicserve/django-envtools
Author-email: Brent O'Connor <brent@epicserve.com>
License-File: LICENSE
Classifier: Development Status :: 3 - Alpha
Classifier: Framework :: Django
Classifier: Framework :: Django :: 4.2
Classifier: Framework :: Django :: 5.1
Classifier: Intended Audience :: Developers
Classifier: License :: OSI Approved :: MIT License
Classifier: Programming Language :: Python
Classifier: Programming Language :: Python :: 3
Classifier: Programming Language :: Python :: 3.10
Classifier: Programming Language :: Python :: 3.11
Classifier: Programming Language :: Python :: 3.12
Classifier: Programming Language :: Python :: 3.13
Classifier: Topic :: Software Development :: Build Tools
Classifier: Topic :: Software Development :: Libraries :: Python Modules
Requires-Python: >=3.10
Requires-Dist: environs[django]>=11.0.0
